[
  {
    "id": "123",
    "date": "2024-06-12",
    "city": "ПИТЕРБУРГСКИ",
    "quantity": 2333,
    "supplyType": "Монопаллета",
    "warehouseName": "Белая дача",
    "warehouseAddress": "пр. Ленинский, д. 7, Новосибирск",
    "status": "В пути"
  },
  {
    "id": "124",
    "date": "2024-06-12",
    "city": "ПИТЕРБУРГСКИ",
    "quantity": 2333,
    "supplyType": "Монопаллета",
    "warehouseName": "Белая дача",
    "warehouseAddress": "пр. Ленинский, д. 7, Новосибирск",
    "status": "В пути"
  }
]